{
    "description": "",
    "tags": [],
    "size": {
        "height": 480,
        "width": 640
    },
    "objects": [
        {
            "id": 7790626,
            "classId": 13302,
            "description": "",
            "geometryType": "rectangle",
            "labelerLogin": "gr@datasetninja.com",
            "createdAt": "2023-06-22T21:03:50.898Z",
            "updatedAt": "2023-06-22T21:03:50.898Z",
            "tags": [],
            "classTitle": "RBC",
            "points": {
                "exterior": [
                    [
                        445,
                        41
                    ],
                    [
                        545,
                        138
                    ]
                ],
                "interior": []
            }
        },
        {
            "id": 7790625,
            "classId": 13302,
            "description": "",
            "geometryType": "rectangle",
            "labelerLogin": "gr@datasetninja.com",
            "createdAt": "2023-06-22T21:03:50.898Z",
            "updatedAt": "2023-06-22T21:03:50.898Z",
            "tags": [],
            "classTitle": "RBC",
            "points": {
                "exterior": [
                    [
                        471,
                        210
                    ],
                    [
                        571,
                        307
                    ]
                ],
                "interior": []
            }
        },
        {
            "id": 7790624,
            "classId": 13302,
            "description": "",
            "geometryType": "rectangle",
            "labelerLogin": "gr@datasetninja.com",
            "createdAt": "2023-06-22T21:03:50.897Z",
            "updatedAt": "2023-06-22T21:03:50.897Z",
            "tags": [],
            "classTitle": "RBC",
            "points": {
                "exterior": [
                    [
                        1,
                        1
                    ],
                    [
                        100,
                        97
                    ]
                ],
                "interior": []
            }
        },
        {
            "id": 7790623,
            "classId": 13302,
            "description": "",
            "geometryType": "rectangle",
            "labelerLogin": "gr@datasetninja.com",
            "createdAt": "2023-06-22T21:03:50.897Z",
            "updatedAt": "2023-06-22T21:03:50.897Z",
            "tags": [],
            "classTitle": "RBC",
            "points": {
                "exterior": [
                    [
                        3,
                        130
                    ],
                    [
                        103,
                        227
                    ]
                ],
                "interior": []
            }
        },
        {
            "id": 7790622,
            "classId": 13302,
            "description": "",
            "geometryType": "rectangle",
            "labelerLogin": "gr@datasetninja.com",
            "createdAt": "2023-06-22T21:03:50.896Z",
            "updatedAt": "2023-06-22T21:03:50.896Z",
            "tags": [],
            "classTitle": "RBC",
            "points": {
                "exterior": [
                    [
                        63,
                        267
                    ],
                    [
                        163,
                        364
                    ]
                ],
                "interior": []
            }
        },
        {
            "id": 7790621,
            "classId": 13302,
            "description": "",
            "geometryType": "rectangle",
            "labelerLogin": "gr@datasetninja.com",
            "createdAt": "2023-06-22T21:03:50.896Z",
            "updatedAt": "2023-06-22T21:03:50.896Z",
            "tags": [],
            "classTitle": "RBC",
            "points": {
                "exterior": [
                    [
                        340,
                        324
                    ],
                    [
                        454,
                        423
                    ]
                ],
                "interior": []
            }
        },
        {
            "id": 7790620,
            "classId": 13302,
            "description": "",
            "geometryType": "rectangle",
            "labelerLogin": "gr@datasetninja.com",
            "createdAt": "2023-06-22T21:03:50.896Z",
            "updatedAt": "2023-06-22T21:03:50.896Z",
            "tags": [],
            "classTitle": "RBC",
            "points": {
                "exterior": [
                    [
                        526,
                        212
                    ],
                    [
                        637,
                        340
                    ]
                ],
                "interior": []
            }
        },
        {
            "id": 7790619,
            "classId": 13302,
            "description": "",
            "geometryType": "rectangle",
            "labelerLogin": "gr@datasetninja.com",
            "createdAt": "2023-06-22T21:03:50.896Z",
            "updatedAt": "2023-06-22T21:03:50.896Z",
            "tags": [],
            "classTitle": "RBC",
            "points": {
                "exterior": [
                    [
                        256,
                        257
                    ],
                    [
                        360,
                        341
                    ]
                ],
                "interior": []
            }
        },
        {
            "id": 7790618,
            "classId": 13302,
            "description": "",
            "geometryType": "rectangle",
            "labelerLogin": "gr@datasetninja.com",
            "createdAt": "2023-06-22T21:03:50.896Z",
            "updatedAt": "2023-06-22T21:03:50.896Z",
            "tags": [],
            "classTitle": "RBC",
            "points": {
                "exterior": [
                    [
                        336,
                        127
                    ],
                    [
                        437,
                        217
                    ]
                ],
                "interior": []
            }
        },
        {
            "id": 7790617,
            "classId": 13302,
            "description": "",
            "geometryType": "rectangle",
            "labelerLogin": "gr@datasetninja.com",
            "createdAt": "2023-06-22T21:03:50.895Z",
            "updatedAt": "2023-06-22T21:03:50.895Z",
            "tags": [],
            "classTitle": "RBC",
            "points": {
                "exterior": [
                    [
                        353,
                        389
                    ],
                    [
                        454,
                        479
                    ]
                ],
                "interior": []
            }
        },
        {
            "id": 7790616,
            "classId": 13304,
            "description": "",
            "geometryType": "rectangle",
            "labelerLogin": "gr@datasetninja.com",
            "createdAt": "2023-06-22T21:03:50.895Z",
            "updatedAt": "2023-06-22T21:03:50.895Z",
            "tags": [],
            "classTitle": "Platelets",
            "points": {
                "exterior": [
                    [
                        187,
                        427
                    ],
                    [
                        231,
                        470
                    ]
                ],
                "interior": []
            }
        },
        {
            "id": 7790615,
            "classId": 13304,
            "description": "",
            "geometryType": "rectangle",
            "labelerLogin": "gr@datasetninja.com",
            "createdAt": "2023-06-22T21:03:50.895Z",
            "updatedAt": "2023-06-22T21:03:50.895Z",
            "tags": [],
            "classTitle": "Platelets",
            "points": {
                "exterior": [
                    [
                        547,
                        386
                    ],
                    [
                        582,
                        417
                    ]
                ],
                "interior": []
            }
        },
        {
            "id": 7790614,
            "classId": 13304,
            "description": "",
            "geometryType": "rectangle",
            "labelerLogin": "gr@datasetninja.com",
            "createdAt": "2023-06-22T21:03:50.894Z",
            "updatedAt": "2023-06-22T21:03:50.894Z",
            "tags": [],
            "classTitle": "Platelets",
            "points": {
                "exterior": [
                    [
                        77,
                        230
                    ],
                    [
                        116,
                        268
                    ]
                ],
                "interior": []
            }
        },
        {
            "id": 7790613,
            "classId": 13304,
            "description": "",
            "geometryType": "rectangle",
            "labelerLogin": "gr@datasetninja.com",
            "createdAt": "2023-06-22T21:03:50.894Z",
            "updatedAt": "2023-06-22T21:03:50.894Z",
            "tags": [],
            "classTitle": "Platelets",
            "points": {
                "exterior": [
                    [
                        98,
                        49
                    ],
                    [
                        143,
                        85
                    ]
                ],
                "interior": []
            }
        },
        {
            "id": 7790612,
            "classId": 13304,
            "description": "",
            "geometryType": "rectangle",
            "labelerLogin": "gr@datasetninja.com",
            "createdAt": "2023-06-22T21:03:50.893Z",
            "updatedAt": "2023-06-22T21:03:50.893Z",
            "tags": [],
            "classTitle": "Platelets",
            "points": {
                "exterior": [
                    [
                        259,
                        1
                    ],
                    [
                        297,
                        26
                    ]
                ],
                "interior": []
            }
        },
        {
            "id": 7790611,
            "classId": 13303,
            "description": "",
            "geometryType": "rectangle",
            "labelerLogin": "gr@datasetninja.com",
            "createdAt": "2023-06-22T21:03:50.893Z",
            "updatedAt": "2023-06-22T21:03:50.893Z",
            "tags": [],
            "classTitle": "WBC",
            "points": {
                "exterior": [
                    [
                        92,
                        45
                    ],
                    [
                        329,
                        266
                    ]
                ],
                "interior": []
            }
        }
    ]
}