{
    "description": "",
    "tags": [],
    "size": {
        "height": 480,
        "width": 640
    },
    "objects": [
        {
            "id": 7789050,
            "classId": 13302,
            "description": "",
            "geometryType": "rectangle",
            "labelerLogin": "gr@datasetninja.com",
            "createdAt": "2023-06-22T21:03:43.066Z",
            "updatedAt": "2023-06-22T21:03:43.066Z",
            "tags": [],
            "classTitle": "RBC",
            "points": {
                "exterior": [
                    [
                        300,
                        365
                    ],
                    [
                        427,
                        474
                    ]
                ],
                "interior": []
            }
        },
        {
            "id": 7789049,
            "classId": 13302,
            "description": "",
            "geometryType": "rectangle",
            "labelerLogin": "gr@datasetninja.com",
            "createdAt": "2023-06-22T21:03:43.066Z",
            "updatedAt": "2023-06-22T21:03:43.066Z",
            "tags": [],
            "classTitle": "RBC",
            "points": {
                "exterior": [
                    [
                        487,
                        17
                    ],
                    [
                        614,
                        126
                    ]
                ],
                "interior": []
            }
        },
        {
            "id": 7789048,
            "classId": 13302,
            "description": "",
            "geometryType": "rectangle",
            "labelerLogin": "gr@datasetninja.com",
            "createdAt": "2023-06-22T21:03:43.066Z",
            "updatedAt": "2023-06-22T21:03:43.066Z",
            "tags": [],
            "classTitle": "RBC",
            "points": {
                "exterior": [
                    [
                        160,
                        200
                    ],
                    [
                        265,
                        300
                    ]
                ],
                "interior": []
            }
        },
        {
            "id": 7789047,
            "classId": 13302,
            "description": "",
            "geometryType": "rectangle",
            "labelerLogin": "gr@datasetninja.com",
            "createdAt": "2023-06-22T21:03:43.066Z",
            "updatedAt": "2023-06-22T21:03:43.066Z",
            "tags": [],
            "classTitle": "RBC",
            "points": {
                "exterior": [
                    [
                        69,
                        8
                    ],
                    [
                        193,
                        109
                    ]
                ],
                "interior": []
            }
        },
        {
            "id": 7789046,
            "classId": 13302,
            "description": "",
            "geometryType": "rectangle",
            "labelerLogin": "gr@datasetninja.com",
            "createdAt": "2023-06-22T21:03:43.065Z",
            "updatedAt": "2023-06-22T21:03:43.065Z",
            "tags": [],
            "classTitle": "RBC",
            "points": {
                "exterior": [
                    [
                        181,
                        91
                    ],
                    [
                        286,
                        191
                    ]
                ],
                "interior": []
            }
        },
        {
            "id": 7789045,
            "classId": 13302,
            "description": "",
            "geometryType": "rectangle",
            "labelerLogin": "gr@datasetninja.com",
            "createdAt": "2023-06-22T21:03:43.065Z",
            "updatedAt": "2023-06-22T21:03:43.065Z",
            "tags": [],
            "classTitle": "RBC",
            "points": {
                "exterior": [
                    [
                        82,
                        280
                    ],
                    [
                        191,
                        394
                    ]
                ],
                "interior": []
            }
        },
        {
            "id": 7789044,
            "classId": 13302,
            "description": "",
            "geometryType": "rectangle",
            "labelerLogin": "gr@datasetninja.com",
            "createdAt": "2023-06-22T21:03:43.065Z",
            "updatedAt": "2023-06-22T21:03:43.065Z",
            "tags": [],
            "classTitle": "RBC",
            "points": {
                "exterior": [
                    [
                        509,
                        252
                    ],
                    [
                        618,
                        366
                    ]
                ],
                "interior": []
            }
        },
        {
            "id": 7789043,
            "classId": 13302,
            "description": "",
            "geometryType": "rectangle",
            "labelerLogin": "gr@datasetninja.com",
            "createdAt": "2023-06-22T21:03:43.064Z",
            "updatedAt": "2023-06-22T21:03:43.064Z",
            "tags": [],
            "classTitle": "RBC",
            "points": {
                "exterior": [
                    [
                        83,
                        128
                    ],
                    [
                        207,
                        253
                    ]
                ],
                "interior": []
            }
        },
        {
            "id": 7789042,
            "classId": 13303,
            "description": "",
            "geometryType": "rectangle",
            "labelerLogin": "gr@datasetninja.com",
            "createdAt": "2023-06-22T21:03:43.064Z",
            "updatedAt": "2023-06-22T21:03:43.064Z",
            "tags": [],
            "classTitle": "WBC",
            "points": {
                "exterior": [
                    [
                        173,
                        358
                    ],
                    [
                        306,
                        479
                    ]
                ],
                "interior": []
            }
        }
    ]
}