{
    "description": "",
    "tags": [],
    "size": {
        "height": 480,
        "width": 640
    },
    "objects": [
        {
            "id": 7790517,
            "classId": 13302,
            "description": "",
            "geometryType": "rectangle",
            "labelerLogin": "gr@datasetninja.com",
            "createdAt": "2023-06-22T21:03:50.886Z",
            "updatedAt": "2023-06-22T21:03:50.886Z",
            "tags": [],
            "classTitle": "RBC",
            "points": {
                "exterior": [
                    [
                        112,
                        140
                    ],
                    [
                        221,
                        242
                    ]
                ],
                "interior": []
            }
        },
        {
            "id": 7790516,
            "classId": 13302,
            "description": "",
            "geometryType": "rectangle",
            "labelerLogin": "gr@datasetninja.com",
            "createdAt": "2023-06-22T21:03:50.885Z",
            "updatedAt": "2023-06-22T21:03:50.885Z",
            "tags": [],
            "classTitle": "RBC",
            "points": {
                "exterior": [
                    [
                        79,
                        45
                    ],
                    [
                        176,
                        148
                    ]
                ],
                "interior": []
            }
        },
        {
            "id": 7790515,
            "classId": 13302,
            "description": "",
            "geometryType": "rectangle",
            "labelerLogin": "gr@datasetninja.com",
            "createdAt": "2023-06-22T21:03:50.884Z",
            "updatedAt": "2023-06-22T21:03:50.884Z",
            "tags": [],
            "classTitle": "RBC",
            "points": {
                "exterior": [
                    [
                        1,
                        254
                    ],
                    [
                        112,
                        366
                    ]
                ],
                "interior": []
            }
        },
        {
            "id": 7790514,
            "classId": 13302,
            "description": "",
            "geometryType": "rectangle",
            "labelerLogin": "gr@datasetninja.com",
            "createdAt": "2023-06-22T21:03:50.882Z",
            "updatedAt": "2023-06-22T21:03:50.882Z",
            "tags": [],
            "classTitle": "RBC",
            "points": {
                "exterior": [
                    [
                        111,
                        345
                    ],
                    [
                        222,
                        454
                    ]
                ],
                "interior": []
            }
        },
        {
            "id": 7790513,
            "classId": 13302,
            "description": "",
            "geometryType": "rectangle",
            "labelerLogin": "gr@datasetninja.com",
            "createdAt": "2023-06-22T21:03:50.882Z",
            "updatedAt": "2023-06-22T21:03:50.882Z",
            "tags": [],
            "classTitle": "RBC",
            "points": {
                "exterior": [
                    [
                        120,
                        258
                    ],
                    [
                        238,
                        363
                    ]
                ],
                "interior": []
            }
        },
        {
            "id": 7790512,
            "classId": 13302,
            "description": "",
            "geometryType": "rectangle",
            "labelerLogin": "gr@datasetninja.com",
            "createdAt": "2023-06-22T21:03:50.882Z",
            "updatedAt": "2023-06-22T21:03:50.882Z",
            "tags": [],
            "classTitle": "RBC",
            "points": {
                "exterior": [
                    [
                        232,
                        52
                    ],
                    [
                        349,
                        186
                    ]
                ],
                "interior": []
            }
        },
        {
            "id": 7790511,
            "classId": 13302,
            "description": "",
            "geometryType": "rectangle",
            "labelerLogin": "gr@datasetninja.com",
            "createdAt": "2023-06-22T21:03:50.881Z",
            "updatedAt": "2023-06-22T21:03:50.881Z",
            "tags": [],
            "classTitle": "RBC",
            "points": {
                "exterior": [
                    [
                        413,
                        121
                    ],
                    [
                        531,
                        226
                    ]
                ],
                "interior": []
            }
        },
        {
            "id": 7790510,
            "classId": 13302,
            "description": "",
            "geometryType": "rectangle",
            "labelerLogin": "gr@datasetninja.com",
            "createdAt": "2023-06-22T21:03:50.880Z",
            "updatedAt": "2023-06-22T21:03:50.880Z",
            "tags": [],
            "classTitle": "RBC",
            "points": {
                "exterior": [
                    [
                        529,
                        265
                    ],
                    [
                        639,
                        373
                    ]
                ],
                "interior": []
            }
        },
        {
            "id": 7790509,
            "classId": 13302,
            "description": "",
            "geometryType": "rectangle",
            "labelerLogin": "gr@datasetninja.com",
            "createdAt": "2023-06-22T21:03:50.879Z",
            "updatedAt": "2023-06-22T21:03:50.879Z",
            "tags": [],
            "classTitle": "RBC",
            "points": {
                "exterior": [
                    [
                        1,
                        1
                    ],
                    [
                        126,
                        100
                    ]
                ],
                "interior": []
            }
        },
        {
            "id": 7790508,
            "classId": 13302,
            "description": "",
            "geometryType": "rectangle",
            "labelerLogin": "gr@datasetninja.com",
            "createdAt": "2023-06-22T21:03:50.879Z",
            "updatedAt": "2023-06-22T21:03:50.879Z",
            "tags": [],
            "classTitle": "RBC",
            "points": {
                "exterior": [
                    [
                        522,
                        73
                    ],
                    [
                        617,
                        197
                    ]
                ],
                "interior": []
            }
        },
        {
            "id": 7790507,
            "classId": 13303,
            "description": "",
            "geometryType": "rectangle",
            "labelerLogin": "gr@datasetninja.com",
            "createdAt": "2023-06-22T21:03:50.877Z",
            "updatedAt": "2023-06-22T21:03:50.877Z",
            "tags": [],
            "classTitle": "WBC",
            "points": {
                "exterior": [
                    [
                        216,
                        152
                    ],
                    [
                        471,
                        387
                    ]
                ],
                "interior": []
            }
        }
    ]
}